marshmallow_autoschema/__init__.py
marshmallow_autoschema/__version__.py
marshmallow_autoschema/schema_factory.py
marshmallow_autoschema/utilities.py
marshmallow_autoschema-0.4.0.dist-info/LICENSE
marshmallow_autoschema-0.4.0.dist-info/METADATA
marshmallow_autoschema-0.4.0.dist-info/WHEEL
marshmallow_autoschema-0.4.0.dist-info/top_level.txt
marshmallow_autoschema-0.4.0.dist-info/RECORD
