Metadata-Version: 2.1
Name: marshmallow-autoschema
Version: 0.4.0
Summary: Generate marshmallow schemas from type annotations and decorators.
Home-page: https://github.com/delvelabs/marshmallow-autoschema
Author: Delve Labs inc.
Author-email: info@delvelabs.ca
License: MIT
Platform: UNKNOWN
Requires-Dist: marshmallow (<4.0,>=3.7.1)
Requires-Dist: marshmallow-enum (==1.5.1)
